bitepy/__init__.py
bitepy/_bitepy.cp38-win_amd64.pyd
bitepy/_bitepy.cpp
bitepy/data.py
bitepy/heatmap.py
bitepy/results.py
bitepy/simulation.py
bitepy-0.6.16.dist-info/METADATA
bitepy-0.6.16.dist-info/WHEEL
bitepy-0.6.16.dist-info/licenses/LICENSE
bitepy-0.6.16.dist-info/RECORD
