Metadata-Version: 2.2
Name: bitepy
Version: 0.6.16
Summary: A Python wrapper for my C++ battery CID arbitrage simulation engine.
Author-Email: David Schaurecker <dschaurecker@gmail.com>
License: MIT License
Classifier: Programming Language :: Python :: 3
Classifier: Programming Language :: Python :: 3.8
Classifier: Programming Language :: Python :: 3.9
Classifier: Programming Language :: Python :: 3.10
Classifier: Programming Language :: Python :: 3.11
Classifier: Programming Language :: Python :: 3.12
Classifier: Programming Language :: Python :: 3.13
Classifier: License :: OSI Approved :: MIT License
Classifier: Operating System :: OS Independent
Classifier: Development Status :: 4 - Beta
Project-URL: Homepage, https://github.com/dschaurecker/bitepy
Project-URL: Issues, https://github.com/dschaurecker/bitepy/issues
Project-URL: Documentation, https://dschaurecker.github.io/bitepy/
Requires-Python: >=3.8
Requires-Dist: numpy>=1.16.0
Requires-Dist: pandas>=0.24.0
Requires-Dist: matplotlib>=3.0.0
Requires-Dist: tqdm>=4.0.0
